README
setup.py
src/daversy/__init__.py
src/daversy/difflib_ext.py
src/daversy/dvs.py
src/daversy/plugins.py
src/daversy/state.py
src/daversy/utils.py
src/daversy.egg-info/PKG-INFO
src/daversy.egg-info/SOURCES.txt
src/daversy.egg-info/dependency_links.txt
src/daversy.egg-info/entry_points.txt
src/daversy.egg-info/requires.txt
src/daversy.egg-info/top_level.txt
src/daversy/command/__init__.py
src/daversy/command/compare.py
src/daversy/command/copy.py
src/daversy/command/generate.py
src/daversy/command/name.py
src/daversy/db/__init__.py
src/daversy/db/object.py
src/daversy/db/oracle/__init__.py
src/daversy/db/oracle/adapter.py
src/daversy/db/oracle/code.py
src/daversy/db/oracle/column.py
src/daversy/db/oracle/connection.py
src/daversy/db/oracle/constraint.py
src/daversy/db/oracle/foreign_key.py
src/daversy/db/oracle/index.py
src/daversy/db/oracle/primary_key.py
src/daversy/db/oracle/sequence.py
src/daversy/db/oracle/state_xsd.py
src/daversy/db/oracle/table.py
src/daversy/db/oracle/trigger.py
src/daversy/db/oracle/unique_key.py
src/daversy/db/oracle/view.py
src/daversy/tools/__init__.py
src/daversy/tools/dvstool_oracle.py