Metadata-Version: 1.1
Name: daversy
Version: 0.3.4
Summary: Daversy is a source control tool for relational databases.
Home-page: https://github.com/kalyptorisk/daversy
Author: Ashish Kulkarni
Author-email: ashish.kulkarni@kalyptorisk.com
License: GPLv2+
Platform: UNKNOWN
Classifier: Development Status :: 5 - Production/Stable
Classifier: Intended Audience :: Developers
Classifier: Intended Audience :: System Administrators
Classifier: License :: OSI Approved :: GNU General Public License v2 or later (GPLv2+)
Classifier: Operating System :: OS Independent
Classifier: Programming Language :: Python
Classifier: Topic :: Database
Classifier: Topic :: Software Development :: Version Control
Classifier: Topic :: Utilities
